docs/.nojekyll
docs/Makefile
docs/index.html
docs/make.bat
docs/doctrees/ecape.doctree
docs/doctrees/ecape_py.doctree
docs/doctrees/environment.pickle
docs/doctrees/example.doctree
docs/doctrees/index.doctree
docs/html/.buildinfo
docs/html/ecape.html
docs/html/ecape_py.html
docs/html/example.html
docs/html/genindex.html
docs/html/index.html
docs/html/objects.inv
docs/html/py-modindex.html
docs/html/search.html
docs/html/searchindex.js
docs/html/_sources/ecape.rst.txt
docs/html/_sources/ecape_py.rst.txt
docs/html/_sources/example.rst.txt
docs/html/_sources/index.rst.txt
docs/html/_static/_sphinx_javascript_frameworks_compat.js
docs/html/_static/basic.css
docs/html/_static/doctools.js
docs/html/_static/documentation_options.js
docs/html/_static/file.png
docs/html/_static/jquery.js
docs/html/_static/language_data.js
docs/html/_static/minus.png
docs/html/_static/plus.png
docs/html/_static/pygments.css
docs/html/_static/searchtools.js
docs/html/_static/sphinx_highlight.js
docs/html/_static/twemoji.css
docs/html/_static/twemoji.js
docs/html/_static/css/badge_only.css
docs/html/_static/css/theme.css
docs/html/_static/css/fonts/Roboto-Slab-Bold.woff
docs/html/_static/css/fonts/Roboto-Slab-Bold.woff2
docs/html/_static/css/fonts/Roboto-Slab-Regular.woff
docs/html/_static/css/fonts/Roboto-Slab-Regular.woff2
docs/html/_static/css/fonts/fontawesome-webfont.eot
docs/html/_static/css/fonts/fontawesome-webfont.svg
docs/html/_static/css/fonts/fontawesome-webfont.ttf
docs/html/_static/css/fonts/fontawesome-webfont.woff
docs/html/_static/css/fonts/fontawesome-webfont.woff2
docs/html/_static/css/fonts/lato-bold-italic.woff
docs/html/_static/css/fonts/lato-bold-italic.woff2
docs/html/_static/css/fonts/lato-bold.woff
docs/html/_static/css/fonts/lato-bold.woff2
docs/html/_static/css/fonts/lato-normal-italic.woff
docs/html/_static/css/fonts/lato-normal-italic.woff2
docs/html/_static/css/fonts/lato-normal.woff
docs/html/_static/css/fonts/lato-normal.woff2
docs/html/_static/js/badge_only.js
ecape-0.1.1.dist-info/METADATA
ecape-0.1.1.dist-info/WHEEL
ecape-0.1.1.dist-info/licenses/LICENSE.txt
ecape-0.1.1.dist-info/RECORD
