Metadata-Version: 2.1
Name: ecape
Version: 0.1.1
Summary: Calculate the entraining CAPE (ECAPE) of a parcel.
Project-URL: Documentation, https://citylikeamradio.github.io/ecape
Project-URL: Issues, https://github.com/citylikeamradio/ecape/issues
Project-URL: Source, https://github.com/citylikeamradio/ecape
Author-email: Robert Capella <bob.capella@gmail.com>
License-Expression: MIT
License-File: LICENSE.txt
Classifier: Development Status :: 4 - Beta
Classifier: Programming Language :: Python
Classifier: Programming Language :: Python :: 3.8
Classifier: Programming Language :: Python :: 3.9
Classifier: Programming Language :: Python :: 3.10
Classifier: Programming Language :: Python :: 3.11
Requires-Python: >=3.8
Requires-Dist: metpy>=1.2.0
Requires-Dist: numpy>=1.21.0
Requires-Dist: pytest
